custom_django_auth_backend/__init__.py
custom_django_auth_backend/backend.py
custom_django_auth_backend/dto.py
custom_django_auth_backend/exceptions.py
custom_django_auth_backend/logging.py
custom_django_auth_backend/settings.py
custom_django_auth_backend/utils.py
custom_django_auth_backend/wrapt.py
custom_django_auth_backend-0.1.3.dist-info/LICENSE
custom_django_auth_backend-0.1.3.dist-info/METADATA
custom_django_auth_backend-0.1.3.dist-info/WHEEL
custom_django_auth_backend-0.1.3.dist-info/top_level.txt
custom_django_auth_backend-0.1.3.dist-info/RECORD
